colarama/__init__.py
colarama/ansi.py
colarama/ansitowin32.py
colarama/initialise.py
colarama/win32.py
colarama/winterm.py
colarama/tests/__init__.py
colarama/tests/ansi_test.py
colarama/tests/ansitowin32_test.py
colarama/tests/initialise_test.py
colarama/tests/isatty_test.py
colarama/tests/utils.py
colarama/tests/winterm_test.py
colarama-2.1.6.dist-info/LICENSE.txt
colarama-2.1.6.dist-info/METADATA
colarama-2.1.6.dist-info/WHEEL
colarama-2.1.6.dist-info/top_level.txt
colarama-2.1.6.dist-info/RECORD
