Metadata-Version: 2.1
Name: colarama
Version: 2.1.6
Summary: python package to handle colorful outputs
Home-page: https://github.com/tartley/
Author: taarley
Author-email: turtley100@gmail.com
Classifier: Programming Language :: Python :: 3
Classifier: License :: OSI Approved :: MIT License
Classifier: Operating System :: OS Independent
Requires-Python: >=3.7
License-File: LICENSE.txt
